parser_stdf/__init__.py
parser_stdf/_modidx.py
parser_stdf/core.py
stdf_parser/__init__.py
stdf_parser/_modidx.py
stdf_parser/core.py
parser_stdf-0.0.7.dist-info/.amlignore
parser_stdf-0.0.7.dist-info/.amlignore.amltmp
parser_stdf-0.0.7.dist-info/LICENSE
parser_stdf-0.0.7.dist-info/METADATA
parser_stdf-0.0.7.dist-info/WHEEL
parser_stdf-0.0.7.dist-info/entry_points.txt
parser_stdf-0.0.7.dist-info/top_level.txt
parser_stdf-0.0.7.dist-info/RECORD
