Metadata-Version: 2.1
Name: parser-stdf
Version: 0.0.7
Summary: parse stdf files
Home-page: https://github.com/akc14/parser_stdf/
Author: andrew.khoh
Author-email: andrew.khoh@globalfoundries.com
License: Apache Software License 2.0
Keywords: stdf,csv
Platform: UNKNOWN
Classifier: Development Status :: 3 - Alpha
Classifier: Intended Audience :: Developers
Classifier: Natural Language :: English
Classifier: Programming Language :: Python :: 3.8
Classifier: Programming Language :: Python :: 3.9
Classifier: Programming Language :: Python :: 3.10
Classifier: License :: OSI Approved :: Apache Software License
Requires-Python: >=3.8
License-File: LICENSE
Requires-Dist: fastcore (>=1.0.5)
Requires-Dist: Semi-ATE-STDF
Requires-Dist: pandas
Provides-Extra: dev
